cachesim/__init__.py
cachesim/cache.py
cachesim/datastructures.py
cachesim/fmt.py
cachesim/hierarchy.py
cachesim/replacement.py
cachesim/statistics.py
pycachesimulator-1.0.2.dist-info/licenses/LICENSE
pycachesimulator-1.0.2.dist-info/METADATA
pycachesimulator-1.0.2.dist-info/WHEEL
pycachesimulator-1.0.2.dist-info/top_level.txt
pycachesimulator-1.0.2.dist-info/RECORD
