Metadata-Version: 2.4
Name: pyCacheSimulator
Version: 1.0.2
Summary: A python library to simulate cache behavior.
Author-email: Bieito Beceiro <bieito.beceiro.fernandez@udc.es>
License-Expression: BSD-3-Clause
Project-URL: Homepage, https://gitlab.com/bieito/pycachesim/
Project-URL: Repository, https://gitlab.com/bieito/pycachesim/
Project-URL: Issues, https://gitlab.com/bieito/pycachesim/-/issues
Classifier: Development Status :: 5 - Production/Stable
Classifier: Environment :: Console
Classifier: Intended Audience :: Education
Classifier: Operating System :: OS Independent
Classifier: Programming Language :: Python :: 3
Classifier: Topic :: System :: Hardware
License-File: LICENSE
Dynamic: license-file
